watermark/__init__.py
watermark/watermark.py
watermark2-1.0.3.dist-info/LICENSE
watermark2-1.0.3.dist-info/METADATA
watermark2-1.0.3.dist-info/WHEEL
watermark2-1.0.3.dist-info/top_level.txt
watermark2-1.0.3.dist-info/RECORD
