Metadata-Version: 2.1
Name: watermark2
Version: 1.0.3
Summary: 给图片添加文字水印，支持设置文字内容、大小、透明度、颜色、旋转等
Home-page: https://github.com/jingle1267/watermark.git
Author: jingle1267
Author-email: jingle1267@163.com
Maintainer: jingle1267
Maintainer-email: jingle1267@163.com
License: MIT
Keywords: watermark
Platform: all
Classifier: Programming Language :: Python :: 3
Classifier: License :: OSI Approved :: MIT License
Classifier: Operating System :: OS Independent
